fpbrowser/__init__.py
fpbrowser/cli/__init__.py
fpbrowser/cli/main.py
fpbrowser/core/__init__.py
fpbrowser/core/browser.py
fpbrowser/core/fingerprint.py
fpbrowser/core/profile.py
fpbrowser/core/zero_profile.py
fpbrowser/data/default_config.json
fpbrowser/storage/__init__.py
fpbrowser/storage/local.py
fpbrowser/storage/s3.py
fpbrowser/storage/s3_library.py
fpbrowser/utils/__init__.py
fpbrowser/utils/chromium_installer.py
fpbrowser/utils/config.py
fpbrowser/utils/fonts_installer.py
fpbrowser/utils/helpers.py
fpbrowser/utils/orbita_installer.py
mp_browser-0.1.13.dist-info/METADATA
mp_browser-0.1.13.dist-info/WHEEL
mp_browser-0.1.13.dist-info/entry_points.txt
mp_browser-0.1.13.dist-info/RECORD
